alpaca_trading_algorithm/__init__.py
alpaca_trading_algorithm/tickerpicker.py
alpaca_trading_algorithm/trader.py
alpaca_trading_algorithm-0.0.3.dist-info/METADATA
alpaca_trading_algorithm-0.0.3.dist-info/WHEEL
alpaca_trading_algorithm-0.0.3.dist-info/top_level.txt
alpaca_trading_algorithm-0.0.3.dist-info/RECORD
