Metadata-Version: 2.1
Name: alpaca-trading-algorithm
Version: 0.0.3
Summary: A package to trade for you!
Home-page: https://github.com/noahxl10/trade-algo
Author: Noah Alex
Author-email: noahxl10@gmail.com
License: UNKNOWN
Platform: UNKNOWN
Classifier: Programming Language :: Python :: 3
Classifier: License :: OSI Approved :: MIT License
Classifier: Operating System :: OS Independent
Requires-Python: >=3.1
Requires-Dist: scipy
Requires-Dist: numpy
Requires-Dist: pandas
Requires-Dist: yfinance
Requires-Dist: seaborn
Requires-Dist: datetime
Requires-Dist: iexfinance
Requires-Dist: alpaca-trade-api
